{
	"name": "pl_source_stage_remove_txn",
	"properties": {
		"activities": [
			{
				"name": "Remove policy data from source stage",
				"type": "SqlServerStoredProcedure",
				"dependsOn": [],
				"policy": {
					"timeout": "0.12:00:00",
					"retry": 0,
					"retryIntervalInSeconds": 30,
					"secureOutput": false,
					"secureInput": false
				},
				"userProperties": [],
				"typeProperties": {
					"storedProcedureName": "[dbo].[removeData]"
				},
				"linkedServiceName": {
					"referenceName": "sourceStageDB",
					"type": "LinkedServiceReference"
				}
			}
		],
		"folder": {
			"name": "utility/cleanup"
		},
		"annotations": []
	}
}